Metadata-Version: 2.4
Name: notifications-api-common
Version: 0.10.1
Summary: Re-usable integration layer for the Common Ground Notifications API specification.
Home-page: https://github.com/maykinmedia/notifications-api-common
Author: Maykin Media
Author-email: support@maykinmedia.nl
License: MIT
Project-URL: Changelog, https://github.com/maykinmedia/notifications-api-common/blob/main/CHANGELOG.rst
Project-URL: Bug Tracker, https://github.com/maykinmedia/notifications-api-common/issues
Project-URL: Source Code, https://github.com/maykinmedia/notifications-api-common
Keywords: notifications,REST,API,Common Ground,ZGW
Classifier: Development Status :: 4 - Beta
Classifier: Framework :: Django
Classifier: Framework :: Django :: 4.2
Classifier: Intended Audience :: Developers
Classifier: Operating System :: Unix
Classifier: Operating System :: MacOS
Classifier: Operating System :: Microsoft :: Windows
Classifier: Programming Language :: Python :: 3.10
Classifier: Programming Language :: Python :: 3.11
Classifier: Programming Language :: Python :: 3.12
Classifier: Topic :: Software Development :: Libraries :: Python Modules
License-File: LICENSE
Requires-Dist: django>=4.2.0
Requires-Dist: django-solo
Requires-Dist: djangorestframework>=3.12.0
Requires-Dist: celery
Requires-Dist: djangorestframework_camel_case>=1.2.0
Requires-Dist: zgw-consumers>=1.0.0
Requires-Dist: ape-pie
Provides-Extra: db
Requires-Dist: psycopg2; extra == "db"
Provides-Extra: tests
Requires-Dist: psycopg2; extra == "tests"
Requires-Dist: pytest; extra == "tests"
Requires-Dist: pytest-django; extra == "tests"
Requires-Dist: freezegun; extra == "tests"
Requires-Dist: tox; extra == "tests"
Requires-Dist: ruff; extra == "tests"
Requires-Dist: zgw-consumers[testutils]>=0.35.1; extra == "tests"
Provides-Extra: coverage
Requires-Dist: pytest-cov; extra == "coverage"
Provides-Extra: setup-configuration
Requires-Dist: django-setup-configuration>=0.7.0; extra == "setup-configuration"
Requires-Dist: furl; extra == "setup-configuration"
Provides-Extra: docs
Requires-Dist: sphinx; extra == "docs"
Requires-Dist: sphinx-rtd-theme; extra == "docs"
Provides-Extra: release
Requires-Dist: bump-my-version; extra == "release"
Requires-Dist: twine; extra == "release"
Dynamic: license-file
